clidle/__init__.py
clidle/__main__.py
clidle/clidle.py
clidle_BlueStag-1.0.dist-info/LICENSE
clidle_BlueStag-1.0.dist-info/METADATA
clidle_BlueStag-1.0.dist-info/WHEEL
clidle_BlueStag-1.0.dist-info/top_level.txt
clidle_BlueStag-1.0.dist-info/RECORD
