Metadata-Version: 2.1
Name: clidle-BlueStag
Version: 1.0
Summary: A Wordle clone for the terminal.
Author: BlueStag
License: UNKNOWN
Platform: UNKNOWN
Classifier: Programming Language :: Python :: 3
Classifier: License :: OSI Approved :: MIT License
Classifier: Operating System :: OS Independent
Classifier: Environment :: Console :: Curses
Classifier: Topic :: Games/Entertainment
Requires-Python: >=3.7
License-File: LICENSE
